pyserial_asyncio-0.5.dist-info/DESCRIPTION.rst
pyserial_asyncio-0.5.dist-info/METADATA
pyserial_asyncio-0.5.dist-info/RECORD
pyserial_asyncio-0.5.dist-info/WHEEL
pyserial_asyncio-0.5.dist-info/metadata.json
pyserial_asyncio-0.5.dist-info/top_level.txt
serial_asyncio/__init__.py
